lab8_1/__init__.py
lab8_1/demo.py
lab8_1/student.py
juliana_laba8_property-0.1.0.dist-info/entry_points.txt
juliana_laba8_property-0.1.0.dist-info/METADATA
juliana_laba8_property-0.1.0.dist-info/WHEEL
juliana_laba8_property-0.1.0.dist-info/RECORD
