Metadata-Version: 2.4
Name: juliana-laba8-property
Version: 0.1.0
Summary: Python package demonstrating property usage with Student class
License: MIT
Author: JTimonina
Author-email: yulianatimonina@gmail.com
Requires-Python: >=3.8
Classifier: Programming Language :: Python :: 3
Classifier: License :: OSI Approved :: MIT License
Classifier: Operating System :: OS Independent
Provides-Extra: dev
Requires-Dist: flake8 (>=7.3.0) ; extra == "dev"
Requires-Dist: pytest (>=9.0.2) ; extra == "dev"
